botway/__init__.py
botway.py-0.0.8.dist-info/LICENSE
botway.py-0.0.8.dist-info/METADATA
botway.py-0.0.8.dist-info/WHEEL
botway.py-0.0.8.dist-info/top_level.txt
botway.py-0.0.8.dist-info/RECORD
