Metadata-Version: 2.1
Name: botway.py
Version: 0.0.8
Summary: Python client package for Botway.
Home-page: https://github.com/abdfnx/botway
Author: abdfnx
License: MIT
Project-URL: Issues, https://github.com/abdfnx/botway/issues
Classifier: Development Status :: 5 - Production/Stable
Classifier: License :: OSI Approved :: MIT License
Classifier: Intended Audience :: Developers
Classifier: Natural Language :: English
Classifier: Operating System :: OS Independent
Classifier: Programming Language :: Python :: 3.8
Classifier: Programming Language :: Python :: 3.9
Classifier: Programming Language :: Python :: 3.10
Classifier: Topic :: Internet
Classifier: Topic :: Software Development :: Libraries
Classifier: Topic :: Software Development :: Libraries :: Python Modules
Classifier: Topic :: Utilities
Requires-Python: >=3.6.0
License-File: LICENSE
